rpsa_sdk/__init__.py
rpsa_sdk/helpers.py
rpsa_sdk/strategy.py
rpsa_sdk-0.1.2.dist-info/LICENCE
rpsa_sdk-0.1.2.dist-info/METADATA
rpsa_sdk-0.1.2.dist-info/WHEEL
rpsa_sdk-0.1.2.dist-info/RECORD
