Metadata-Version: 2.1
Name: rpsa-sdk
Version: 0.1.2
Summary: A minimal SDK for authoring Rock-Paper-Scissors strategies compatible with the RPS Arena backend.
License: MIT
Keywords: rpsa,rock-paper-scissors,strategy,sdk
Author: Your Name
Author-email: you@example.com
Requires-Python: >=3.9,<4.0
Classifier: Development Status :: 4 - Beta
Classifier: Intended Audience :: Developers
Classifier: License :: OSI Approved :: MIT License
Classifier: Programming Language :: Python :: 3
Classifier: Programming Language :: Python :: 3.9
Classifier: Programming Language :: Python :: 3.10
Classifier: Programming Language :: Python :: 3.11
Classifier: Programming Language :: Python :: 3.12
Classifier: Topic :: Games/Entertainment
